pysmi/__init__.py
pysmi/borrower/__init__.py
pysmi/borrower/anyfile.py
pysmi/borrower/base.py
pysmi/borrower/pyfile.py
pysmi/codegen/__init__.py
pysmi/codegen/base.py
pysmi/codegen/intermediate.py
pysmi/codegen/jfilters.py
pysmi/codegen/jsondoc.py
pysmi/codegen/null.py
pysmi/codegen/pysnmp.py
pysmi/codegen/symtable.py
pysmi/codegen/templates/jsondoc/base.j2
pysmi/codegen/templates/pysnmp/base.j2
pysmi/codegen/templates/pysnmp/managed-objects-instances.j2
pysmi/codegen/templates/pysnmp/mib-definitions.j2
pysmi/codegen/templates/pysnmp/mib-instrumentation/managed-objects-instances.j2
pysmi/codegen/templates/pysnmp/mib-instrumentation/managed-objects.j2
pysmi/compat.py
pysmi/compiler.py
pysmi/config.py
pysmi/debug.py
pysmi/error.py
pysmi/lexer/__init__.py
pysmi/lexer/base.py
pysmi/lexer/smi.py
pysmi/mibinfo.py
pysmi/parser/__init__.py
pysmi/parser/base.py
pysmi/parser/dialect.py
pysmi/parser/null.py
pysmi/parser/smi.py
pysmi/parser/smiv1.py
pysmi/parser/smiv1compat.py
pysmi/parser/smiv2.py
pysmi/reader/__init__.py
pysmi/reader/base.py
pysmi/reader/callback.py
pysmi/reader/httpclient.py
pysmi/reader/localfile.py
pysmi/reader/url.py
pysmi/reader/zipreader.py
pysmi/scripts/mibcopy.py
pysmi/scripts/mibdump.py
pysmi/searcher/__init__.py
pysmi/searcher/anyfile.py
pysmi/searcher/base.py
pysmi/searcher/pyfile.py
pysmi/searcher/pypackage.py
pysmi/searcher/stub.py
pysmi/writer/__init__.py
pysmi/writer/base.py
pysmi/writer/callback.py
pysmi/writer/localfile.py
pysmi/writer/pyfile.py
pysmi_lextudio-1.4.2.dist-info/LICENSE.rst
pysmi_lextudio-1.4.2.dist-info/METADATA
pysmi_lextudio-1.4.2.dist-info/WHEEL
pysmi_lextudio-1.4.2.dist-info/entry_points.txt
pysmi_lextudio-1.4.2.dist-info/RECORD
